[
  {
    "Experiment":"TransformerSE (baseline)",
    "exp_id":"transformer_se",
    "N":22,
    "accuracy_mean":0.8587545455,
    "accuracy_std":0.0848954468,
    "accuracy_ci_low":0.821114013,
    "accuracy_ci_high":0.8963950779,
    "f1_mean":0.8782272727,
    "f1_std":0.0824069414,
    "f1_ci_low":0.8416900818,
    "f1_ci_high":0.9147644637,
    "precision_mean":0.8559136364,
    "precision_std":0.1152739069,
    "precision_ci_low":0.8048040493,
    "precision_ci_high":0.9070232235,
    "recall_mean":0.9112318182,
    "recall_std":0.0729303607,
    "recall_ci_low":0.8788963077,
    "recall_ci_high":0.9435673286,
    "auc_mean":0.8524590909,
    "auc_std":0.0812279547,
    "auc_ci_low":0.8164446334,
    "auc_ci_high":0.8884735484
  },
  {
    "Experiment":"Single (No Pos)",
    "exp_id":"single_no_pos",
    "N":22,
    "accuracy_mean":0.8307772727,
    "accuracy_std":0.0980397924,
    "accuracy_ci_low":0.787308864,
    "accuracy_ci_high":0.8742456815,
    "f1_mean":0.8587727273,
    "f1_std":0.0837819345,
    "f1_ci_low":0.8216258985,
    "f1_ci_high":0.895919556,
    "precision_mean":0.8397136364,
    "precision_std":0.1316501146,
    "precision_ci_low":0.7813432456,
    "precision_ci_high":0.8980840272,
    "recall_mean":0.8973363636,
    "recall_std":0.0963158126,
    "recall_ci_low":0.8546323247,
    "recall_ci_high":0.9400404026,
    "auc_mean":0.8233681818,
    "auc_std":0.1087417403,
    "auc_ci_low":0.7751547952,
    "auc_ci_high":0.8715815685
  },
  {
    "Experiment":"Single + Pos Encoding",
    "exp_id":"single_with_pos",
    "N":22,
    "accuracy_mean":0.7949954545,
    "accuracy_std":0.1219996037,
    "accuracy_ci_low":0.7409038605,
    "accuracy_ci_high":0.8490870485,
    "f1_mean":0.8356,
    "f1_std":0.0995619023,
    "f1_ci_low":0.7914567255,
    "f1_ci_high":0.8797432745,
    "precision_mean":0.7960818182,
    "precision_std":0.1425410071,
    "precision_ci_low":0.7328826762,
    "precision_ci_high":0.8592809602,
    "recall_mean":0.9010409091,
    "recall_std":0.0988243447,
    "recall_ci_low":0.8572246493,
    "recall_ci_high":0.9448571689,
    "auc_mean":0.7785272727,
    "auc_std":0.1275510063,
    "auc_ci_low":0.7219743247,
    "auc_ci_high":0.8350802208
  },
  {
    "Experiment":"Dual (No Pos)",
    "exp_id":"dual_no_pos",
    "N":22,
    "accuracy_mean":0.8176045455,
    "accuracy_std":0.1011612408,
    "accuracy_ci_low":0.772752164,
    "accuracy_ci_high":0.8624569269,
    "f1_mean":0.8434818182,
    "f1_std":0.0960608321,
    "f1_ci_low":0.8008908312,
    "f1_ci_high":0.8860728051,
    "precision_mean":0.8249136364,
    "precision_std":0.1297043315,
    "precision_ci_low":0.7674059574,
    "precision_ci_high":0.8824213153,
    "recall_mean":0.8787409091,
    "recall_std":0.1091800159,
    "recall_ci_low":0.8303332019,
    "recall_ci_high":0.9271486163,
    "auc_mean":0.8115045455,
    "auc_std":0.1016550679,
    "auc_ci_low":0.7664332133,
    "auc_ci_high":0.8565758776
  },
  {
    "Experiment":"Dual + Pos Encoding",
    "exp_id":"dual_with_pos",
    "N":22,
    "accuracy_mean":0.7824090909,
    "accuracy_std":0.1576815987,
    "accuracy_ci_low":0.7124969866,
    "accuracy_ci_high":0.8523211952,
    "f1_mean":0.8143636364,
    "f1_std":0.1389746861,
    "f1_ci_low":0.7527457125,
    "f1_ci_high":0.8759815602,
    "precision_mean":0.8221409091,
    "precision_std":0.1345952474,
    "precision_ci_low":0.7624647195,
    "precision_ci_high":0.8818170986,
    "recall_mean":0.8477136364,
    "recall_std":0.1789096321,
    "recall_ci_low":0.7683895493,
    "recall_ci_high":0.9270377234,
    "auc_mean":0.7936181818,
    "auc_std":0.1098652015,
    "auc_ci_low":0.7449066803,
    "auc_ci_high":0.8423296833
  }
]